JavaKaiyuanXiangmuZhongwenWendang20160514/README.md
JavaKaiyuanXiangmuZhongwenWendang20160514/__init__.py
JavaKaiyuanXiangmuZhongwenWendang20160514/__main__.py
JavaKaiyuanXiangmuZhongwenWendang20160514/file.epub
JavaKaiyuanXiangmuZhongwenWendang20160514/index.html
JavaKaiyuanXiangmuZhongwenWendang20160514/css/__init__.py
JavaKaiyuanXiangmuZhongwenWendang20160514/css/annotations.css
JavaKaiyuanXiangmuZhongwenWendang20160514/css/main.css
JavaKaiyuanXiangmuZhongwenWendang20160514/css/normalize.css
JavaKaiyuanXiangmuZhongwenWendang20160514/css/popup.css
JavaKaiyuanXiangmuZhongwenWendang20160514/font/__init__.py
JavaKaiyuanXiangmuZhongwenWendang20160514/font/fontello.eot
JavaKaiyuanXiangmuZhongwenWendang20160514/font/fontello.svg
JavaKaiyuanXiangmuZhongwenWendang20160514/font/fontello.ttf
JavaKaiyuanXiangmuZhongwenWendang20160514/font/fontello.woff
JavaKaiyuanXiangmuZhongwenWendang20160514/img/__init__.py
JavaKaiyuanXiangmuZhongwenWendang20160514/img/annotator-glyph-sprite.png
JavaKaiyuanXiangmuZhongwenWendang20160514/img/annotator-icon-sprite.png
JavaKaiyuanXiangmuZhongwenWendang20160514/img/apple-touch-icon.png
JavaKaiyuanXiangmuZhongwenWendang20160514/img/cancelfullscreen.png
JavaKaiyuanXiangmuZhongwenWendang20160514/img/close.png
JavaKaiyuanXiangmuZhongwenWendang20160514/img/fullscreen.png
JavaKaiyuanXiangmuZhongwenWendang20160514/img/loader.gif
JavaKaiyuanXiangmuZhongwenWendang20160514/img/menu-icon.png
JavaKaiyuanXiangmuZhongwenWendang20160514/img/save.png
JavaKaiyuanXiangmuZhongwenWendang20160514/img/saved.png
JavaKaiyuanXiangmuZhongwenWendang20160514/img/settings-s.png
JavaKaiyuanXiangmuZhongwenWendang20160514/img/settings.png
JavaKaiyuanXiangmuZhongwenWendang20160514/img/star.png
JavaKaiyuanXiangmuZhongwenWendang20160514/js/__init__.py
JavaKaiyuanXiangmuZhongwenWendang20160514/js/epub.js
JavaKaiyuanXiangmuZhongwenWendang20160514/js/epub.min.js
JavaKaiyuanXiangmuZhongwenWendang20160514/js/epub.min.map
JavaKaiyuanXiangmuZhongwenWendang20160514/js/hooks.min.js
java_kaiyuan_xiangmu_zhongwen_wendang_20160514-2024.3.2.0.dist-info/METADATA
java_kaiyuan_xiangmu_zhongwen_wendang_20160514-2024.3.2.0.dist-info/WHEEL
java_kaiyuan_xiangmu_zhongwen_wendang_20160514-2024.3.2.0.dist-info/entry_points.txt
java_kaiyuan_xiangmu_zhongwen_wendang_20160514-2024.3.2.0.dist-info/top_level.txt
java_kaiyuan_xiangmu_zhongwen_wendang_20160514-2024.3.2.0.dist-info/RECORD
